{
  "generator-jhipster": {
    "applicationType": "monolith",
    "gitCompany": "",
    "baseName": "CassandraDynamoLDAP",
    "packageName": "com.rhanberry.protodynamo",
    "packageFolder": "com/rhanberry/protodynamo",
    "serverPort": 8080,
    "serviceDiscoveryType": false,
    "authenticationType": "jwt",
    "uaaBaseName": "../uaa",
    "cacheProvider": "no",
    "enableHibernateCache": false,
    "websocket": false,
    "databaseType": "cassandra",
    "devDatabaseType": "cassandra",
    "prodDatabaseType": "cassandra",
    "searchEngine": false,
    "enableSwaggerCodegen": false,
    "messageBroker": false,
    "buildTool": "maven",
    "useSass": true,
    "clientPackageManager": "npm",
    "testFrameworks": [],
    "enableTranslation": true,
    "nativeLanguage": "en",
    "languages": ["en"],
    "clientFramework": "react",
    "jhiPrefix": "jhi",
    "jhipsterVersion": "6.6.0",
    "jwtSecretKey": "NzcyZTYyNzVmYjc1MTc3MGI5MmQ0ODJhYjQzNTU1ZjQ3MzlkZTFjMTY3ZmFiMjljNzdjMDNjZTZkNmQwZTcyY2NmNTg3Y2RmYWJiNGVlNzU2NGM2MDdkZDg3NTk5NWQ2M2MyOGY0ODQwYjU1MGM2NzkxZTk2YTUwNzFhN2NmYTQ=",
    "embeddableLaunchScript": false,
    "clientTheme": "none",
    "creationTimestamp": 1578432701845,
    "entitySuffix": "",
    "dtoSuffix": "DTO",
    "otherModules": [],
    "blueprints": []
  },
  "git-provider": "GitHub",
  "git-company": "rhanberry",
  "repository-name": "Cass-dynamo-migration"
}
